pacparser/__init__.py
pacparser/_pacparser.cp311-win_amd64.pyd
pacparser/__pycache__/__init__.cpython-311.pyc
pacparser-1.4.5.dist-info/METADATA
pacparser-1.4.5.dist-info/WHEEL
pacparser-1.4.5.dist-info/top_level.txt
pacparser-1.4.5.dist-info/RECORD
