Metadata-Version: 2.1
Name: pacparser
Version: 1.4.5
Summary: Pacparser package
Home-page: https://github.com/manugarg/pacparser
Author: Manu Garg
Author-email: manugarg@gmail.com
License: LGPL
